molSim/__init__.py
molSim-0.0.7.dist-info/METADATA
molSim-0.0.7.dist-info/WHEEL
molSim-0.0.7.dist-info/top_level.txt
molSim-0.0.7.dist-info/RECORD
