Metadata-Version: 2.1
Name: molSim
Version: 0.0.7
Summary: This package has been renamed to AIMSim, please use `pip install aimsim`
Author-email: Jackson Burns <jwburns@mit.edu>, Himaghna Bhattacharjee <himaghna@udel.edu>
License: MIT
Project-URL: Homepage, https://github.com/VlachosGroup/AIMSim
Classifier: Programming Language :: Python :: 3
